pyros_setup/__init__.py
pyros_setup/__main__.py
pyros_setup/_version.py
pyros_setup/ros_setup.py
pyros_setup/utils.py
pyros_setup/tests/conftest.py
pyros_setup/tests/test_setup.py
pyros_setup-0.3.0.dist-info/DESCRIPTION.rst
pyros_setup-0.3.0.dist-info/METADATA
pyros_setup-0.3.0.dist-info/RECORD
pyros_setup-0.3.0.dist-info/WHEEL
pyros_setup-0.3.0.dist-info/entry_points.txt
pyros_setup-0.3.0.dist-info/metadata.json
pyros_setup-0.3.0.dist-info/top_level.txt
pyros_setup-0.3.0.dist-info/zip-safe
