Metadata-Version: 1.0
Name: pyros_setup
Version: 0.3.0
Summary: Toolsuite for running ROS environments directly from python code, without any specific requirements outside of usual python
Home-page: http://github.com/asmodehn/pyros-setup
Author: AlexV
Author-email: asmodehn@gmail.com
License: BSD
Platform: UNKNOWN
